ickle/__init__.py
tests/__init__.py
tests/test_dataframe.py
ickle-1.0.4.dist-info/LICENSE
ickle-1.0.4.dist-info/METADATA
ickle-1.0.4.dist-info/WHEEL
ickle-1.0.4.dist-info/top_level.txt
ickle-1.0.4.dist-info/RECORD
