Metadata-Version: 2.1
Name: ickle
Version: 1.0.4
Summary: 🔍 Experimental DataFrame, statistics and analysis library for Python
Home-page: https://github.com/karishmashuklaa/ickle
Author: Karishma Shukla
Author-email: karishmashuklaa@gmail.com
License: MIT
Keywords: data-analysis,numpy,data,python,library,pandas,ickle,datascience
Classifier: Intended Audience :: Developers
Classifier: Programming Language :: Python :: 3
Classifier: Operating System :: Unix
Classifier: Operating System :: MacOS :: MacOS X
Classifier: Operating System :: Microsoft :: Windows
License-File: LICENSE
Requires-Dist: numpy
Requires-Dist: pytest
